{"is_source_file": true, "format": "js", "description": ".js file: TodoInput.js", "external_files": [], "external_methods": [], "published": [], "classes": [], "methods": [], "calls": [], "search-terms": ["TodoInput.js", "js"], "state": 2, "file_id": 15, "knowledge_revision": 51, "git_revision": "f0dd790aff19f87f2feca5b1e149d871ec3f109a", "ctags": [], "filename": "frontend/src/components/TodoInput.js", "format-version": 4, "code-base-name": "https://github.com/kavia-common/frontend-capability-tester-307533-307542.git:kavia-main", "revision_history": [{"51": "f0dd790aff19f87f2feca5b1e149d871ec3f109a"}]}